discatpy/__init__.py
discatpy-0.0.0.post1.dist-info/METADATA
discatpy-0.0.0.post1.dist-info/WHEEL
discatpy-0.0.0.post1.dist-info/top_level.txt
discatpy-0.0.0.post1.dist-info/RECORD
